README.md
setup.py
akeva/__init__.py
akeva/akeva.py
akeva.egg-info/PKG-INFO
akeva.egg-info/SOURCES.txt
akeva.egg-info/dependency_links.txt
akeva.egg-info/not-zip-safe
akeva.egg-info/requires.txt
akeva.egg-info/top_level.txt