Metadata-Version: 1.0
Name: akeva
Version: 0.0.1
Summary: akeva is an adapter for the Advania Key Vault - A GCP Secrets Manager with secrets stored in GCS.
Home-page: https://gitlab.com/advania-analytics/internal-projects/advania-key-vault/akeva-adapter
Author: Me
Author-email: alexanderjb@advania.is
License: MIT
Platform: UNKNOWN
